{"nodes": [{"id": "home_elyes_projects_stealthy_firmware_src_wifi_wifideauth_cpp", "label": "WifiDeauth.cpp", "file_type": "code", "source_file": "src/wifi/WifiDeauth.cpp", "source_location": "L1"}, {"id": "wifi_wifideauth_promisccallback", "label": "promiscCallback()", "file_type": "code", "source_file": "src/wifi/WifiDeauth.cpp", "source_location": "L10"}, {"id": "wifi_promiscuous_pkt_type_t", "label": "wifi_promiscuous_pkt_type_t", "file_type": "code", "source_file": "src/wifi/WifiDeauth.cpp", "source_location": "L10"}, {"id": "wifi_wifideauth_scan", "label": "scan()", "file_type": "code", "source_file": "src/wifi/WifiDeauth.cpp", "source_location": "L47"}, {"id": "wifi_wifideauth_startdeauth", "label": "startDeauth()", "file_type": "code", "source_file": "src/wifi/WifiDeauth.cpp", "source_location": "L77"}, {"id": "wifi_wifideauth_stop", "label": "stop()", "file_type": "code", "source_file": "src/wifi/WifiDeauth.cpp", "source_location": "L110"}, {"id": "wifi_wifideauth_isrunning", "label": "isRunning()", "file_type": "code", "source_file": "src/wifi/WifiDeauth.cpp", "source_location": "L123"}, {"id": "wifi_wifideauth_rssilabel", "label": "rssiLabel()", "file_type": "code", "source_file": "src/wifi/WifiDeauth.cpp", "source_location": "L128"}, {"id": "wifi_wifideauth_deauthtask", "label": "deauthTask()", "file_type": "code", "source_file": "src/wifi/WifiDeauth.cpp", "source_location": "L137"}, {"id": "wifi_wifideauth_runloop", "label": "runLoop()", "file_type": "code", "source_file": "src/wifi/WifiDeauth.cpp", "source_location": "L142"}, {"id": "wifi_wifideauth_senddeauthframe", "label": "sendDeauthFrame()", "file_type": "code", "source_file": "src/wifi/WifiDeauth.cpp", "source_location": "L157"}], "edges": [{"source": "home_elyes_projects_stealthy_firmware_src_wifi_wifideauth_cpp", "target": "home_elyes_projects_stealthy_firmware_src_wifi_wifideauth_h", "relation": "imports", "context": "import", "confidence": "EXTRACTED", "source_file": "src/wifi/WifiDeauth.cpp", "source_location": "L1", "weight": 1.0}, {"source": "home_elyes_projects_stealthy_firmware_src_wifi_wifideauth_cpp", "target": "wifi", "relation": "imports", "context": "import", "confidence": "EXTRACTED", "source_file": "src/wifi/WifiDeauth.cpp", "source_location": "L2", "weight": 1.0}, {"source": "home_elyes_projects_stealthy_firmware_src_wifi_wifideauth_cpp", "target": "esp_wifi", "relation": "imports", "context": "import", "confidence": "EXTRACTED", "source_file": "src/wifi/WifiDeauth.cpp", "source_location": "L3", "weight": 1.0}, {"source": "home_elyes_projects_stealthy_firmware_src_wifi_wifideauth_cpp", "target": "wifi_wifideauth_promisccallback", "relation": "contains", "confidence": "EXTRACTED", "source_file": "src/wifi/WifiDeauth.cpp", "source_location": "L10", "weight": 1.0}, {"source": "wifi_wifideauth_promisccallback", "target": "wifi_promiscuous_pkt_type_t", "relation": "references", "confidence": "EXTRACTED", "source_file": "src/wifi/WifiDeauth.cpp", "source_location": "L10", "weight": 1.0, "context": "parameter_type"}, {"source": "home_elyes_projects_stealthy_firmware_src_wifi_wifideauth_cpp", "target": "wifi_wifideauth_scan", "relation": "contains", "confidence": "EXTRACTED", "source_file": "src/wifi/WifiDeauth.cpp", "source_location": "L47", "weight": 1.0}, {"source": "home_elyes_projects_stealthy_firmware_src_wifi_wifideauth_cpp", "target": "wifi_wifideauth_startdeauth", "relation": "contains", "confidence": "EXTRACTED", "source_file": "src/wifi/WifiDeauth.cpp", "source_location": "L77", "weight": 1.0}, {"source": "home_elyes_projects_stealthy_firmware_src_wifi_wifideauth_cpp", "target": "wifi_wifideauth_stop", "relation": "contains", "confidence": "EXTRACTED", "source_file": "src/wifi/WifiDeauth.cpp", "source_location": "L110", "weight": 1.0}, {"source": "home_elyes_projects_stealthy_firmware_src_wifi_wifideauth_cpp", "target": "wifi_wifideauth_isrunning", "relation": "contains", "confidence": "EXTRACTED", "source_file": "src/wifi/WifiDeauth.cpp", "source_location": "L123", "weight": 1.0}, {"source": "home_elyes_projects_stealthy_firmware_src_wifi_wifideauth_cpp", "target": "wifi_wifideauth_rssilabel", "relation": "contains", "confidence": "EXTRACTED", "source_file": "src/wifi/WifiDeauth.cpp", "source_location": "L128", "weight": 1.0}, {"source": "home_elyes_projects_stealthy_firmware_src_wifi_wifideauth_cpp", "target": "wifi_wifideauth_deauthtask", "relation": "contains", "confidence": "EXTRACTED", "source_file": "src/wifi/WifiDeauth.cpp", "source_location": "L137", "weight": 1.0}, {"source": "home_elyes_projects_stealthy_firmware_src_wifi_wifideauth_cpp", "target": "wifi_wifideauth_runloop", "relation": "contains", "confidence": "EXTRACTED", "source_file": "src/wifi/WifiDeauth.cpp", "source_location": "L142", "weight": 1.0}, {"source": "home_elyes_projects_stealthy_firmware_src_wifi_wifideauth_cpp", "target": "wifi_wifideauth_senddeauthframe", "relation": "contains", "confidence": "EXTRACTED", "source_file": "src/wifi/WifiDeauth.cpp", "source_location": "L157", "weight": 1.0}, {"source": "wifi_wifideauth_deauthtask", "target": "wifi_wifideauth_runloop", "relation": "calls", "context": "call", "confidence": "EXTRACTED", "source_file": "src/wifi/WifiDeauth.cpp", "source_location": "L138", "weight": 1.0}, {"source": "wifi_wifideauth_runloop", "target": "wifi_wifideauth_senddeauthframe", "relation": "calls", "context": "call", "confidence": "EXTRACTED", "source_file": "src/wifi/WifiDeauth.cpp", "source_location": "L146", "weight": 1.0}], "raw_calls": [{"caller_nid": "wifi_wifideauth_promisccallback", "callee": "memcmp", "is_member_call": false, "source_file": "/home/elyes/projects/stealthy-firmware/src/wifi/WifiDeauth.cpp", "source_location": "L31"}, {"caller_nid": "wifi_wifideauth_promisccallback", "callee": "memcmp", "is_member_call": false, "source_file": "/home/elyes/projects/stealthy-firmware/src/wifi/WifiDeauth.cpp", "source_location": "L32"}, {"caller_nid": "wifi_wifideauth_promisccallback", "callee": "memcmp", "is_member_call": false, "source_file": "/home/elyes/projects/stealthy-firmware/src/wifi/WifiDeauth.cpp", "source_location": "L33"}, {"caller_nid": "wifi_wifideauth_scan", "callee": "clear", "is_member_call": true, "source_file": "/home/elyes/projects/stealthy-firmware/src/wifi/WifiDeauth.cpp", "source_location": "L48"}, {"caller_nid": "wifi_wifideauth_scan", "callee": "esp_wifi_get_mode", "is_member_call": false, "source_file": "/home/elyes/projects/stealthy-firmware/src/wifi/WifiDeauth.cpp", "source_location": "L52"}, {"caller_nid": "wifi_wifideauth_scan", "callee": "mode", "is_member_call": true, "source_file": "/home/elyes/projects/stealthy-firmware/src/wifi/WifiDeauth.cpp", "source_location": "L53"}, {"caller_nid": "wifi_wifideauth_scan", "callee": "mode", "is_member_call": true, "source_file": "/home/elyes/projects/stealthy-firmware/src/wifi/WifiDeauth.cpp", "source_location": "L54"}, {"caller_nid": "wifi_wifideauth_scan", "callee": "disconnect", "is_member_call": true, "source_file": "/home/elyes/projects/stealthy-firmware/src/wifi/WifiDeauth.cpp", "source_location": "L57"}, {"caller_nid": "wifi_wifideauth_scan", "callee": "scanNetworks", "is_member_call": true, "source_file": "/home/elyes/projects/stealthy-firmware/src/wifi/WifiDeauth.cpp", "source_location": "L59"}, {"caller_nid": "wifi_wifideauth_scan", "callee": "SSID", "is_member_call": true, "source_file": "/home/elyes/projects/stealthy-firmware/src/wifi/WifiDeauth.cpp", "source_location": "L64"}, {"caller_nid": "wifi_wifideauth_scan", "callee": "RSSI", "is_member_call": true, "source_file": "/home/elyes/projects/stealthy-firmware/src/wifi/WifiDeauth.cpp", "source_location": "L65"}, {"caller_nid": "wifi_wifideauth_scan", "callee": "channel", "is_member_call": true, "source_file": "/home/elyes/projects/stealthy-firmware/src/wifi/WifiDeauth.cpp", "source_location": "L66"}, {"caller_nid": "wifi_wifideauth_scan", "callee": "BSSID", "is_member_call": true, "source_file": "/home/elyes/projects/stealthy-firmware/src/wifi/WifiDeauth.cpp", "source_location": "L67"}, {"caller_nid": "wifi_wifideauth_scan", "callee": "memcpy", "is_member_call": false, "source_file": "/home/elyes/projects/stealthy-firmware/src/wifi/WifiDeauth.cpp", "source_location": "L68"}, {"caller_nid": "wifi_wifideauth_scan", "callee": "push_back", "is_member_call": true, "source_file": "/home/elyes/projects/stealthy-firmware/src/wifi/WifiDeauth.cpp", "source_location": "L69"}, {"caller_nid": "wifi_wifideauth_scan", "callee": "scanDelete", "is_member_call": true, "source_file": "/home/elyes/projects/stealthy-firmware/src/wifi/WifiDeauth.cpp", "source_location": "L72"}, {"caller_nid": "wifi_wifideauth_scan", "callee": "printf", "is_member_call": true, "source_file": "/home/elyes/projects/stealthy-firmware/src/wifi/WifiDeauth.cpp", "source_location": "L73"}, {"caller_nid": "wifi_wifideauth_scan", "callee": "size", "is_member_call": true, "source_file": "/home/elyes/projects/stealthy-firmware/src/wifi/WifiDeauth.cpp", "source_location": "L73"}, {"caller_nid": "wifi_wifideauth_startdeauth", "callee": "size", "is_member_call": true, "source_file": "/home/elyes/projects/stealthy-firmware/src/wifi/WifiDeauth.cpp", "source_location": "L79"}, {"caller_nid": "wifi_wifideauth_startdeauth", "callee": "esp_wifi_set_promiscuous", "is_member_call": false, "source_file": "/home/elyes/projects/stealthy-firmware/src/wifi/WifiDeauth.cpp", "source_location": "L89"}, {"caller_nid": "wifi_wifideauth_startdeauth", "callee": "esp_wifi_set_promiscuous_rx_cb", "is_member_call": false, "source_file": "/home/elyes/projects/stealthy-firmware/src/wifi/WifiDeauth.cpp", "source_location": "L90"}, {"caller_nid": "wifi_wifideauth_startdeauth", "callee": "esp_wifi_set_channel", "is_member_call": false, "source_file": "/home/elyes/projects/stealthy-firmware/src/wifi/WifiDeauth.cpp", "source_location": "L92"}, {"caller_nid": "wifi_wifideauth_startdeauth", "callee": "xTaskCreatePinnedToCore", "is_member_call": false, "source_file": "/home/elyes/projects/stealthy-firmware/src/wifi/WifiDeauth.cpp", "source_location": "L95"}, {"caller_nid": "wifi_wifideauth_startdeauth", "callee": "esp_wifi_set_promiscuous", "is_member_call": false, "source_file": "/home/elyes/projects/stealthy-firmware/src/wifi/WifiDeauth.cpp", "source_location": "L101"}, {"caller_nid": "wifi_wifideauth_startdeauth", "callee": "esp_wifi_set_promiscuous_rx_cb", "is_member_call": false, "source_file": "/home/elyes/projects/stealthy-firmware/src/wifi/WifiDeauth.cpp", "source_location": "L102"}, {"caller_nid": "wifi_wifideauth_startdeauth", "callee": "println", "is_member_call": true, "source_file": "/home/elyes/projects/stealthy-firmware/src/wifi/WifiDeauth.cpp", "source_location": "L106"}, {"caller_nid": "wifi_wifideauth_stop", "callee": "delay", "is_member_call": false, "source_file": "/home/elyes/projects/stealthy-firmware/src/wifi/WifiDeauth.cpp", "source_location": "L113"}, {"caller_nid": "wifi_wifideauth_stop", "callee": "esp_wifi_set_promiscuous", "is_member_call": false, "source_file": "/home/elyes/projects/stealthy-firmware/src/wifi/WifiDeauth.cpp", "source_location": "L115"}, {"caller_nid": "wifi_wifideauth_stop", "callee": "esp_wifi_set_promiscuous_rx_cb", "is_member_call": false, "source_file": "/home/elyes/projects/stealthy-firmware/src/wifi/WifiDeauth.cpp", "source_location": "L116"}, {"caller_nid": "wifi_wifideauth_stop", "callee": "printf", "is_member_call": true, "source_file": "/home/elyes/projects/stealthy-firmware/src/wifi/WifiDeauth.cpp", "source_location": "L120"}, {"caller_nid": "wifi_wifideauth_deauthtask", "callee": "vTaskDelete", "is_member_call": false, "source_file": "/home/elyes/projects/stealthy-firmware/src/wifi/WifiDeauth.cpp", "source_location": "L139"}, {"caller_nid": "wifi_wifideauth_runloop", "callee": "size", "is_member_call": true, "source_file": "/home/elyes/projects/stealthy-firmware/src/wifi/WifiDeauth.cpp", "source_location": "L144"}, {"caller_nid": "wifi_wifideauth_runloop", "callee": "vTaskDelay", "is_member_call": false, "source_file": "/home/elyes/projects/stealthy-firmware/src/wifi/WifiDeauth.cpp", "source_location": "L150"}, {"caller_nid": "wifi_wifideauth_runloop", "callee": "pdMS_TO_TICKS", "is_member_call": false, "source_file": "/home/elyes/projects/stealthy-firmware/src/wifi/WifiDeauth.cpp", "source_location": "L150"}, {"caller_nid": "wifi_wifideauth_runloop", "callee": "vTaskDelay", "is_member_call": false, "source_file": "/home/elyes/projects/stealthy-firmware/src/wifi/WifiDeauth.cpp", "source_location": "L153"}, {"caller_nid": "wifi_wifideauth_runloop", "callee": "pdMS_TO_TICKS", "is_member_call": false, "source_file": "/home/elyes/projects/stealthy-firmware/src/wifi/WifiDeauth.cpp", "source_location": "L153"}, {"caller_nid": "wifi_wifideauth_senddeauthframe", "callee": "memset", "is_member_call": false, "source_file": "/home/elyes/projects/stealthy-firmware/src/wifi/WifiDeauth.cpp", "source_location": "L163"}, {"caller_nid": "wifi_wifideauth_senddeauthframe", "callee": "memset", "is_member_call": false, "source_file": "/home/elyes/projects/stealthy-firmware/src/wifi/WifiDeauth.cpp", "source_location": "L166"}, {"caller_nid": "wifi_wifideauth_senddeauthframe", "callee": "memcpy", "is_member_call": false, "source_file": "/home/elyes/projects/stealthy-firmware/src/wifi/WifiDeauth.cpp", "source_location": "L167"}, {"caller_nid": "wifi_wifideauth_senddeauthframe", "callee": "memcpy", "is_member_call": false, "source_file": "/home/elyes/projects/stealthy-firmware/src/wifi/WifiDeauth.cpp", "source_location": "L168"}, {"caller_nid": "wifi_wifideauth_senddeauthframe", "callee": "esp_wifi_80211_tx", "is_member_call": false, "source_file": "/home/elyes/projects/stealthy-firmware/src/wifi/WifiDeauth.cpp", "source_location": "L172"}, {"caller_nid": "wifi_wifideauth_senddeauthframe", "callee": "memcpy", "is_member_call": false, "source_file": "/home/elyes/projects/stealthy-firmware/src/wifi/WifiDeauth.cpp", "source_location": "L177"}, {"caller_nid": "wifi_wifideauth_senddeauthframe", "callee": "esp_wifi_80211_tx", "is_member_call": false, "source_file": "/home/elyes/projects/stealthy-firmware/src/wifi/WifiDeauth.cpp", "source_location": "L181"}]}